{
    "@context": "http://environment.data.gov.uk/flood-monitoring/meta/context.jsonld",
    "meta": {
        "publisher": "Environment Agency",
        "licence": "http://www.nationalarchives.gov.uk/doc/open-government-licence/version/3/",
        "documentation": "http://environment.data.gov.uk/flood-monitoring/doc/reference",
        "version": "0.9",
        "comment": "Status: Beta service",
        "hasFormat": [
            "http://environment.data.gov.uk/flood-monitoring/id/floods.csv?county=Gloucestershire",
            "http://environment.data.gov.uk/flood-monitoring/id/floods.rdf?county=Gloucestershire",
            "http://environment.data.gov.uk/flood-monitoring/id/floods.ttl?county=Gloucestershire",
            "http://environment.data.gov.uk/flood-monitoring/id/floods.html?county=Gloucestershire"
        ]
    },
    "items": [
        {
            "@id": "http://environment.data.gov.uk/flood-monitoring/id/floods/031WAF213",
            "description": "River Leadon catchment",
            "eaAreaName": "West Midlands",
            "eaRegionName": "No longer used",
            "floodArea": {
                "@id": "http://environment.data.gov.uk/flood-monitoring/id/floodAreas/031WAF213",
                "county": "Gloucestershire, Herefordshire, Worcestershire",
                "notation": "031WAF213",
                "polygon": "http://environment.data.gov.uk/flood-monitoring/id/floodAreas/031WAF213/polygon",
                "riverOrSea": "Leadon, Glynch"
            },
            "floodAreaID": "031WAF213",
            "isTidal": false,
            "message": "River levels are currently rising due to overnight rainfall.  Flooding is possible throughout today, Saturday 29 November 2025. Flooding may affect low lying land and roads adjacent to the River Leadon. Locations that may be affected include Ledbury, Much Marcle, Staunton, Tibberton and Wedderburn Bridge. We are closely monitoring the situation. Avoid using low lying footpaths and any bridges near local watercourses. This message will be updated by 5:00PM on 29 November 2025 or as the situation changes.\n",
            "severity": "Flood alert",
            "severityLevel": 3,
            "timeMessageChanged": "2025-11-29T07:47:00",
            "timeRaised": "2025-11-29T07:47:55",
            "timeSeverityChanged": "2025-11-28T16:08:00"
        },
        {
            "@id": "http://environment.data.gov.uk/flood-monitoring/id/floods/031WAF119",
            "description": "River Wye in Herefordshire",
            "eaAreaName": "West Midlands",
            "eaRegionName": "No longer used",
            "floodArea": {
                "@id": "http://environment.data.gov.uk/flood-monitoring/id/floodAreas/031WAF119",
                "county": "Gloucestershire, Herefordshire",
                "notation": "031WAF119",
                "polygon": "http://environment.data.gov.uk/flood-monitoring/id/floodAreas/031WAF119/polygon",
                "riverOrSea": "River Wye"
            },
            "floodAreaID": "031WAF119",
            "isTidal": false,
            "message": "Rising river levels today may lead to flooding.  Flooding is possible from today 29 November 2025 .  Flooding may affect low lying land and roads along the River Wye from Hay on Wye to Ross on Wye. Other locations affected may include the A438 between Letton & Willersey, Byford, Bredwardine & Hereford. Road closures & diversions on the A438 may be in force. Predicted peaks:- Hay on Wye 1.8m to 2.1m on 29/11 PM, Bredwardine 3.6m to 4.0m on 29/11 evening, Belmont 3.7m to 4.1m on 30/11 AM, Old Wye Bridge 3.1m to 3.6m on 30/11 AM, Mordiford 3.3m to 3.8m on 30/11 AM, Ross on Wye 2.5m to 3.0m on 30/11 PM.  We are closely monitoring the situation .  Take care and avoid walking, cycling or driving through flood water .  This message will be updated by 10:00AM on 30 November 2025 or as the situation changes.\n",
            "severity": "Flood alert",
            "severityLevel": 3,
            "timeMessageChanged": "2025-11-29T10:11:00",
            "timeRaised": "2025-11-29T10:11:12",
            "timeSeverityChanged": "2025-11-28T16:38:00"
        },
        {
            "@id": "http://environment.data.gov.uk/flood-monitoring/id/floods/031WAF215",
            "description": "Rivers in the Forest of Dean",
            "eaAreaName": "West Midlands",
            "eaRegionName": "No longer used",
            "floodArea": {
                "@id": "http://environment.data.gov.uk/flood-monitoring/id/floodAreas/031WAF215",
                "county": "Gloucestershire",
                "notation": "031WAF215",
                "polygon": "http://environment.data.gov.uk/flood-monitoring/id/floodAreas/031WAF215/polygon",
                "riverOrSea": "Lyd, Cinderford Brook"
            },
            "floodAreaID": "031WAF215",
            "isTidal": false,
            "message": "River levels are currently rising due to overnight rainfall.\u202f Flooding is possible throughout today Saturday 29 November 2025. Flooding may affect low lying land and roads adjacent to the river from Gloucester to Chepstow. Other locations that may be affected include Westbury and Lydney.\u202f We are closely monitoring the situation.\u202f Avoid using low lying footpaths and any bridges near local watercourses .\u202f  \n\nThis message will be updated by 5:00pm on 29 November 2025 or as the situation changes.\n",
            "severity": "Flood alert",
            "severityLevel": 3,
            "timeMessageChanged": "2025-11-29T08:16:00",
            "timeRaised": "2025-11-29T08:16:21",
            "timeSeverityChanged": "2025-11-28T16:10:00"
        }
    ]
}